{"ts": "2025-08-24T04:51:06.187807+00:00", "online": true, "symbol": "SOLUSDC", "price": 209.09, "confidence": 0.7546285390853882, "rf_signal": 1, "mom_ok": true, "rsi_ok": true, "sentiment": {"positive": 0.3261716365814209, "neutral": 0.040821779519319534, "negative": 0.6330065727233887}, "active_trades": 1, "balance_clean": 363.55435167999997, "regime": {"scale": 0.35, "block": false, "reasons": ["BTC<EMA200(1h/4h): scale 0.5", "Depth imbalance +82% persistent: scale 0.7"]}, "equity": 432.28624967999997, "unrealized_pnl": 0.07750000000000057}