{"ts": "2025-08-26T05:42:06.178472+00:00", "online": true, "symbol": "SOLUSDC", "price": 189.04, "confidence": 0.7563626766204834, "rf_signal": 1, "mom_ok": true, "rsi_ok": true, "sentiment": {"positive": 0.3473735749721527, "neutral": 0.11898808181285858, "negative": 0.5336383581161499}, "active_trades": 3, "balance_clean": 730.98973877, "regime": {"scale": 0.3, "block": false, "reasons": ["SOL<EMA200(1h): scale 0.60", "BTC<EMA200(1h/4h): scale 0.5"]}, "equity": 989.6456237699999, "unrealized_pnl": 0.629889999999989}